airbotics/__init__.py
airbotics/account.py
airbotics/api_keys.py
airbotics/client.py
airbotics/consts.py
airbotics/exceptions.py
airbotics/maps.py
airbotics-1.4.0.dist-info/LICENSE
airbotics-1.4.0.dist-info/METADATA
airbotics-1.4.0.dist-info/WHEEL
airbotics-1.4.0.dist-info/top_level.txt
airbotics-1.4.0.dist-info/RECORD
