Metadata-Version: 2.1
Name: airbotics
Version: 1.4.0
Summary: Python SDK for Airbotics
Home-page: UNKNOWN
Maintainer: Airbotics
Maintainer-email: hello@airbotics.io
License: Apache-2.0
Project-URL: Source, https://github.com/Airbotics/python-sdk
Project-URL: Tracker, https://github.com/Airbotics/python-sdk/issues
Keywords: robotics,ros,ros2,slam
Platform: UNKNOWN
Classifier: Development Status :: 4 - Beta
Classifier: Intended Audience :: Developers
Classifier: License :: OSI Approved :: Apache Software License
Classifier: Programming Language :: Python :: 3
Classifier: Programming Language :: Python :: 3.8
Requires-Python: >=3.8
Requires-Dist: requests (==2.25.1)
Requires-Dist: numpy (==1.21.0)
Requires-Dist: Pillow (==8.3.1)
